{
    "file_id": "aHR0cHM6Ly9haTEwMmZvcm0yNzI1MjE5NTYuYmxvYi5jb3JlLndpbmRvd3MubmV0L21hcmdpZXMvY29sbGF0ZXJhbC9EdWJhaSUyMEJyb2NodXJlLnBkZg2",
    "file_name": "Dubai Brochure.pdf",
    "url": "https://ai102form272521956.blob.core.windows.net/margies/collateral/Dubai%20Brochure.pdf",
    "language": "en",
    "sentiment": "neutral",
    "key_phrases": [
        {
            "phrase": "The Deira Hotel Family-run hotel"
        },
        {
            "phrase": "The Lost City Hotel"
        },
        {
            "phrase": "The Creek Hotel"
        },
        {
            "phrase": "Friendly boutique hotel"
        },
        {
            "phrase": "The Burj Khalifa"
        },
        {
            "phrase": "Federal Supreme Council"
        },
        {
            "phrase": "Dubai-Sharjah-Ajman metropolitan area"
        },
        {
            "phrase": "following accommodation options"
        },
        {
            "phrase": "traditional commercial center"
        },
        {
            "phrase": "United Arab Emirates"
        },
        {
            "phrase": "Dubai Creek area"
        },
        {
            "phrase": "Luxurious accommodation"
        },
        {
            "phrase": "Traditional Boat"
        },
        {
            "phrase": "populous city"
        },
        {
            "phrase": "seven emirates"
        },
        {
            "phrase": "two emirates"
        },
        {
            "phrase": "southeast coast"
        },
        {
            "phrase": "Persian Gulf"
        },
        {
            "phrase": "Abu Dhabi"
        },
        {
            "phrase": "critical matters"
        },
        {
            "phrase": "national importance"
        },
        {
            "phrase": "northern coastline"
        },
        {
            "phrase": "Travel Presents"
        },
        {
            "phrase": "Dubai Hotels"
        },
        {
            "phrase": "Margie"
        },
        {
            "phrase": "largest"
        },
        {
            "phrase": "capital"
        },
        {
            "phrase": "country"
        },
        {
            "phrase": "veto"
        },
        {
            "phrase": "power"
        },
        {
            "phrase": "heart"
        },
        {
            "phrase": "bustling"
        },
        {
            "phrase": "waterpark"
        },
        {
            "phrase": "aquarium"
        },
        {
            "phrase": "trip"
        },
        {
            "phrase": "night"
        }
    ],
    "locations": [
        {
            "location": "United"
        },
        {
            "location": "Arab Emirates"
        },
        {
            "location": "Persian Gulf"
        },
        {
            "location": "Emirate of Dubai"
        },
        {
            "location": "Dubai"
        },
        {
            "location": "Dhabi"
        },
        {
            "location": "Dubai-Sharjah-Ajman metropolitan area"
        },
        {
            "location": "Deira"
        },
        {
            "location": "The Lost City"
        },
        {
            "location": "Burj Khalifa"
        },
        {
            "location": "Boat"
        },
        {
            "location": "Dubai Creek"
        }
    ],
    "image_tags": [
        {
            "tag": "building"
        },
        {
            "tag": "skyscraper"
        },
        {
            "tag": "sky"
        },
        {
            "tag": "landmark"
        },
        {
            "tag": "metropolis"
        },
        {
            "tag": "metropolitan area"
        },
        {
            "tag": "city"
        },
        {
            "tag": "outdoor"
        },
        {
            "tag": "spire"
        },
        {
            "tag": "tower block"
        },
        {
            "tag": "urban area"
        },
        {
            "tag": "night"
        },
        {
            "tag": "tower"
        },
        {
            "tag": "skyline"
        },
        {
            "tag": "outdoor"
        },
        {
            "tag": "sky"
        },
        {
            "tag": "watercraft"
        },
        {
            "tag": "transport"
        },
        {
            "tag": "cloud"
        },
        {
            "tag": "ship"
        },
        {
            "tag": "water"
        },
        {
            "tag": "building"
        },
        {
            "tag": "lake"
        },
        {
            "tag": "vehicle"
        },
        {
            "tag": "large"
        },
        {
            "tag": "boat"
        },
        {
            "tag": "architecture"
        }
    ]
}